<?xml version="1.0" encoding="UTF-8"?>
<HIGHSCORES>

    <SCORE>
        <NAME>kite</NAME>
        <POINTS>842</POINTS>
    </SCORE>

    <SCORE>
        <NAME>Ejnaer</NAME>
        <POINTS>928</POINTS>
    </SCORE>

    <SCORE>
        <NAME>TatungJDC</NAME>
        <POINTS>448</POINTS>
    </SCORE>
    <SCORE>
        <NAME>NSD4rKn3SS</NAME>
        <POINTS>0</POINTS>
    </SCORE>
    <SCORE>
        <NAME>NSD4rKn3SS</NAME>
        <POINTS>58</POINTS>
    </SCORE>
    <SCORE>
        <NAME>NSD4rKn3SS</NAME>
        <POINTS>332</POINTS>
    </SCORE>
    <SCORE>
        <NAME>NSD4rKn3SS</NAME>
        <POINTS>458</POINTS>
    </SCORE>
    <SCORE>
        <NAME>Blaze</NAME>
        <POINTS>564</POINTS>
    </SCORE>
    <SCORE>
        <NAME>Blaze</NAME>
        <POINTS>756</POINTS>
    </SCORE>
    <SCORE>
        <NAME>Blaze</NAME>
        <POINTS>190</POINTS>
    </SCORE>
    <SCORE>
        <NAME>S</NAME>
        <POINTS>226</POINTS>
    </SCORE>
    <SCORE>
        <NAME>S</NAME>
        <POINTS>438</POINTS>
    </SCORE>
    <SCORE>
        <NAME>S</NAME>
        <POINTS>94</POINTS>
    </SCORE>
    <SCORE>
        <NAME>S</NAME>
        <POINTS>248</POINTS>
    </SCORE>
    <SCORE>
        <NAME>TatungJDC</NAME>
        <POINTS>236</POINTS>
    </SCORE>
    <SCORE>
        <NAME>NSD4rKn3SS</NAME>
        <POINTS>0</POINTS>
    </SCORE>
    <SCORE>
        <NAME>NSD4rKn3SS</NAME>
        <POINTS>546</POINTS>
    </SCORE>
</HIGHSCORES>

